{
  "bundle_id": "site-dynamic-transition-pages-schema-fix",
  "files": [
    {
      "action": "replace",
      "path": "transition-release-index.html"
    },
    {
      "action": "replace",
      "path": "transition-development-status.html"
    },
    {
      "action": "replace",
      "path": "transition-proof-surface.html"
    },
    {
      "action": "replace",
      "path": "stage6-unified-gate-results.html"
    },
    {
      "action": "replace",
      "path": "transition-verification-guide.html"
    },
    {
      "action": "replace",
      "path": "stage10-canonical-release.html"
    },
    {
      "action": "replace",
      "path": "assets/js/transition-page-renderer.js"
    },
    {
      "action": "replace",
      "path": "assets/css/transition-pages.css"
    },
    {
      "action": "replace",
      "path": "data/formalism-tests/transition-proof-surface.json"
    },
    {
      "action": "replace",
      "path": "data/formalism-tests/transition-table-classes.json"
    },
    {
      "action": "replace",
      "path": "data/formalism-tests/transition-table-v1-rc1/index.json"
    },
    {
      "action": "replace",
      "path": "data/formalism-tests/transition-table-v1-rc1/canonical_transition_table_release.json"
    },
    {
      "action": "replace",
      "path": "data/formalism-tests/transition-table-v1-rc1/canonical_transition_table_release.sha256"
    },
    {
      "action": "replace",
      "path": "data/formalism-tests/transition-table-v1-rc1/stage10_canonical_release_report.json"
    },
    {
      "action": "replace",
      "path": "data/formalism-tests/transition-table-v1-rc1/replay_packet.json"
    },
    {
      "action": "replace",
      "path": "data/formalism-tests/transition-table-v1-rc1/release_receipt.json"
    },
    {
      "action": "create_or_replace",
      "path": "docs/DYNAMIC_TRANSITION_SCHEMA_FIX.md"
    },
    {
      "action": "include",
      "path": "README.bundle.md"
    },
    {
      "action": "include",
      "path": "bundle_manifest.json"
    }
  ],
  "no_workflows": true,
  "purpose": "Fix dynamic transition page schema mismatch by upgrading proof-surface JSON and making renderer backward-compatible.",
  "schema": "stegverse_bundle_manifest.v1",
  "target_repo": "StegVerse-Labs/Site"
}
