{
  "generated_at": "2026-05-10T10:59:35Z",
  "schema": "stegverse.experimental_ledger_summary.v1",
  "display_order": "newest_first",
  "recent_runs": [
    {
      "run_id": "T16-self_modifying_rule_sweep_v1-0015",
      "element_id": "T16",
      "experiment": "self_modifying_rule_sweep_v1",
      "status": "completed",
      "sandbox": "open_boundary_deterministic",
      "automation_gate": "scheduled_ready"
    },
    {
      "run_id": "T15-irreversibility_sweep_v1-0014",
      "element_id": "T15",
      "experiment": "irreversibility_sweep_v1",
      "status": "completed",
      "sandbox": "open_boundary_deterministic",
      "automation_gate": "scheduled_ready"
    },
    {
      "run_id": "T14-reconstruction_sweep_v1-0013",
      "element_id": "T14",
      "experiment": "reconstruction_sweep_v1",
      "status": "completed",
      "sandbox": "receipt_evidence_deterministic",
      "automation_gate": "bounded_batch"
    },
    {
      "run_id": "T13-receipt_bound_sweep_v1-0012",
      "element_id": "T13",
      "experiment": "receipt_bound_sweep_v1",
      "status": "completed",
      "sandbox": "receipt_evidence_deterministic",
      "automation_gate": "bounded_batch"
    },
    {
      "run_id": "T12-consensus_sweep_v1-0011",
      "element_id": "T12",
      "experiment": "consensus_sweep_v1",
      "status": "completed",
      "sandbox": "coupled_state_deterministic",
      "automation_gate": "bounded_batch"
    },
    {
      "run_id": "T11-conflict_sweep_v1-0010",
      "element_id": "T11",
      "experiment": "conflict_sweep_v1",
      "status": "completed",
      "sandbox": "coupled_state_deterministic",
      "automation_gate": "bounded_batch"
    },
    {
      "run_id": "T10-multi_agent_sweep_v1-0009",
      "element_id": "T10",
      "experiment": "multi_agent_sweep_v1",
      "status": "completed",
      "sandbox": "coupled_state_deterministic",
      "automation_gate": "bounded_batch"
    },
    {
      "run_id": "T9-two_state_coupling_sweep_v1-0008",
      "element_id": "T9",
      "experiment": "two_state_coupling_sweep_v1",
      "status": "completed",
      "sandbox": "coupled_state_deterministic",
      "automation_gate": "bounded_batch"
    },
    {
      "run_id": "T8-trust_drift_sweep_v1-0007",
      "element_id": "T8",
      "experiment": "trust_drift_sweep_v1",
      "status": "completed",
      "sandbox": "lag_aware_deterministic",
      "automation_gate": "bounded_batch"
    },
    {
      "run_id": "T7-actuation_lag_sweep_v1-0006",
      "element_id": "T7",
      "experiment": "actuation_lag_sweep_v1",
      "status": "completed",
      "sandbox": "lag_aware_deterministic",
      "automation_gate": "sequence_lag_row"
    }
  ],
  "recent_ledger_rows": [
    {
      "timestamp": "2026-05-10T02:02:28Z",
      "element_id": "T16",
      "mode": "self_modifying_rule_sweep_v1",
      "run_id": "T16-self_modifying_rule_sweep_v1-0015-003",
      "tested_property": "self_modifying_rule_safety",
      "constraint_result": "PASS",
      "invariant": null,
      "verdict": "ALLOW",
      "receipt_hash": "sha256:9f0f7b288ddcf0ed71465814ca929b01c0785a1ee2660451b08040ece93b43ec"
    },
    {
      "timestamp": "2026-05-10T02:02:28Z",
      "element_id": "T16",
      "mode": "self_modifying_rule_sweep_v1",
      "run_id": "T16-self_modifying_rule_sweep_v1-0015-002",
      "tested_property": "self_modifying_rule_safety",
      "constraint_result": "FAIL",
      "invariant": null,
      "verdict": "DENY",
      "receipt_hash": "sha256:26ffa22208e52fcbcb700b123e8dc3e09af1571f68453804787874e1e6679b0d"
    },
    {
      "timestamp": "2026-05-10T02:02:28Z",
      "element_id": "T16",
      "mode": "self_modifying_rule_sweep_v1",
      "run_id": "T16-self_modifying_rule_sweep_v1-0015-001",
      "tested_property": "self_modifying_rule_safety",
      "constraint_result": "PASS",
      "invariant": null,
      "verdict": "ALLOW",
      "receipt_hash": "sha256:866330ae7b0708f3a73a6605fb70ccae982b907bfd07a5cfced1aba95016a8d4"
    },
    {
      "timestamp": "2026-05-10T01:54:10Z",
      "element_id": "T15",
      "mode": "irreversibility_sweep_v1",
      "run_id": "T15-irreversibility_sweep_v1-0014-003",
      "tested_property": "irreversibility",
      "constraint_result": "PASS",
      "invariant": 0.0296,
      "verdict": "DENY",
      "receipt_hash": "sha256:d20539130191c88f793bcb9b329d79fa1a3578cde5ea70f037730658e651af41"
    },
    {
      "timestamp": "2026-05-10T01:54:10Z",
      "element_id": "T15",
      "mode": "irreversibility_sweep_v1",
      "run_id": "T15-irreversibility_sweep_v1-0014-002",
      "tested_property": "irreversibility",
      "constraint_result": "PASS",
      "invariant": -0.2733,
      "verdict": "ALLOW",
      "receipt_hash": "sha256:76baa192fa2932679cc53e599a9d01bf73a3ff9ffe937738834ab32908726f98"
    },
    {
      "timestamp": "2026-05-10T01:54:10Z",
      "element_id": "T15",
      "mode": "irreversibility_sweep_v1",
      "run_id": "T15-irreversibility_sweep_v1-0014-001",
      "tested_property": "irreversibility",
      "constraint_result": "PASS",
      "invariant": -0.08598,
      "verdict": "ALLOW",
      "receipt_hash": "sha256:1819c75259875d8734bd4d0deb1c1ebc21f8593daf35fe4d708e459edcf83b88"
    },
    {
      "timestamp": "2026-05-10T01:48:33Z",
      "element_id": "T14",
      "mode": "reconstruction_sweep_v1",
      "run_id": "T14-reconstruction_sweep_v1-0013-003",
      "tested_property": "receipt_reconstruction",
      "constraint_result": "PASS",
      "invariant": -0.11263,
      "verdict": "ALLOW",
      "receipt_hash": "sha256:a9a138da82c5ee25e1cbd9c254491b9f540c220202e8e75782dadb5d9d2f88ef"
    },
    {
      "timestamp": "2026-05-10T01:48:33Z",
      "element_id": "T14",
      "mode": "reconstruction_sweep_v1",
      "run_id": "T14-reconstruction_sweep_v1-0013-002",
      "tested_property": "receipt_reconstruction",
      "constraint_result": "PASS",
      "invariant": -0.13709,
      "verdict": "ALLOW",
      "receipt_hash": "sha256:e5f84a7bb0817a7f069158417696647d9e6fb5298ed6ffa5ebd919dc5a2b7028"
    },
    {
      "timestamp": "2026-05-10T01:48:33Z",
      "element_id": "T14",
      "mode": "reconstruction_sweep_v1",
      "run_id": "T14-reconstruction_sweep_v1-0013-001",
      "tested_property": "receipt_reconstruction",
      "constraint_result": "PASS",
      "invariant": -0.15686,
      "verdict": "ALLOW",
      "receipt_hash": "sha256:b286947f15bae4b270ae903a46bbaf9bcf6e1530db9ee92d129693bd831ac552"
    },
    {
      "timestamp": "2026-05-10T01:43:15Z",
      "element_id": "T13",
      "mode": "receipt_bound_sweep_v1",
      "run_id": "T13-receipt_bound_sweep_v1-0012-003",
      "tested_property": "receipt_bound_transition",
      "constraint_result": "PASS",
      "invariant": -0.11263,
      "verdict": "ALLOW",
      "receipt_hash": "sha256:e48a571e83b6e9443b4061d46feb755d44abb6c5daccc2ac1e71e181eb419227"
    },
    {
      "timestamp": "2026-05-10T01:43:15Z",
      "element_id": "T13",
      "mode": "receipt_bound_sweep_v1",
      "run_id": "T13-receipt_bound_sweep_v1-0012-002",
      "tested_property": "receipt_bound_transition",
      "constraint_result": "PASS",
      "invariant": -0.13709,
      "verdict": "ALLOW",
      "receipt_hash": "sha256:cb5ae14a595f9190af96c59d910b1a43d4d1fd0446074cb5f0832e03f39032dc"
    },
    {
      "timestamp": "2026-05-10T01:43:15Z",
      "element_id": "T13",
      "mode": "receipt_bound_sweep_v1",
      "run_id": "T13-receipt_bound_sweep_v1-0012-001",
      "tested_property": "receipt_bound_transition",
      "constraint_result": "PASS",
      "invariant": -0.15686,
      "verdict": "ALLOW",
      "receipt_hash": "sha256:b530df4396faa47c2f9ebe448ead3c424e9bf7b6fe0b4d9cef7cc24f3bd9b4fa"
    },
    {
      "timestamp": "2026-05-10T01:08:21Z",
      "element_id": "T12",
      "mode": "consensus_sweep_v1",
      "run_id": "T12-consensus_sweep_v1-0011-003",
      "tested_property": "validator_consensus",
      "constraint_result": "PASS",
      "invariant": -0.12549,
      "verdict": "ALLOW",
      "receipt_hash": "sha256:0545133e2d9e48a60f5a9ece87698d80af843582007c4401ec774738954d6ce2"
    },
    {
      "timestamp": "2026-05-10T01:08:21Z",
      "element_id": "T12",
      "mode": "consensus_sweep_v1",
      "run_id": "T12-consensus_sweep_v1-0011-002",
      "tested_property": "validator_consensus",
      "constraint_result": "PASS",
      "invariant": -0.06739,
      "verdict": "ALLOW",
      "receipt_hash": "sha256:afd4c95bc5bf5623ee010bee470eea1b15e8ebfb9b86901dcd0086ada43ab8f8"
    },
    {
      "timestamp": "2026-05-10T01:08:21Z",
      "element_id": "T12",
      "mode": "consensus_sweep_v1",
      "run_id": "T12-consensus_sweep_v1-0011-001",
      "tested_property": "validator_consensus",
      "constraint_result": "PASS",
      "invariant": -0.13728,
      "verdict": "ALLOW",
      "receipt_hash": "sha256:91d7573ba2f2b2aac266bff05b21bc2fc1084c551530ed5428ce629e0d38f366"
    },
    {
      "timestamp": "2026-05-10T00:59:44Z",
      "element_id": "T11",
      "mode": "conflict_sweep_v1",
      "run_id": "T11-conflict_sweep_v1-0010-003",
      "tested_property": "conflict_resolution",
      "constraint_result": "PASS",
      "invariant": -0.0273,
      "verdict": "ALLOW",
      "receipt_hash": "sha256:30035bfbafea16ad3d62563e6fc5ea13a58d23072071a1db0d8d96fbb2a1f52b"
    },
    {
      "timestamp": "2026-05-10T00:59:44Z",
      "element_id": "T11",
      "mode": "conflict_sweep_v1",
      "run_id": "T11-conflict_sweep_v1-0010-002",
      "tested_property": "conflict_resolution",
      "constraint_result": "PASS",
      "invariant": -0.1735,
      "verdict": "ALLOW",
      "receipt_hash": "sha256:2c97511b27a538e690dd59936a10e76dd6de7d77256f092f2316159d897da915"
    },
    {
      "timestamp": "2026-05-10T00:59:44Z",
      "element_id": "T11",
      "mode": "conflict_sweep_v1",
      "run_id": "T11-conflict_sweep_v1-0010-001",
      "tested_property": "conflict_resolution",
      "constraint_result": "PASS",
      "invariant": -0.06684,
      "verdict": "ALLOW",
      "receipt_hash": "sha256:374aa723c451a6fbb20efa06f9b353ad5650e19ca6f88924126d9abe500f6b3b"
    },
    {
      "timestamp": "2026-05-10T00:46:16Z",
      "element_id": "T10",
      "mode": "multi_agent_sweep_v1",
      "run_id": "T10-multi_agent_sweep_v1-0009-003",
      "tested_property": "multi_agent_composition",
      "constraint_result": "PASS",
      "invariant": -0.01517,
      "verdict": "ALLOW",
      "receipt_hash": "sha256:0ae623ac1d728cfd9bf280c099c8ae43f785e756cd2b483ac961e38ee1749301"
    },
    {
      "timestamp": "2026-05-10T00:46:16Z",
      "element_id": "T10",
      "mode": "multi_agent_sweep_v1",
      "run_id": "T10-multi_agent_sweep_v1-0009-002",
      "tested_property": "multi_agent_composition",
      "constraint_result": "PASS",
      "invariant": -0.08448,
      "verdict": "ALLOW",
      "receipt_hash": "sha256:6a8bbf7725c2d950a9379896cfc111962aa4d638a081cc7eea091ee1a4d60248"
    }
  ],
  "verifier_events": []
}
